demo.py
androidtvremote2/__init__.py
androidtvremote2/androidtv_remote.py
androidtvremote2/base.py
androidtvremote2/certificate_generator.py
androidtvremote2/const.py
androidtvremote2/exceptions.py
androidtvremote2/model.py
androidtvremote2/pairing.py
androidtvremote2/polo_pb2.py
androidtvremote2/polo_pb2.pyi
androidtvremote2/py.typed
androidtvremote2/remote.py
androidtvremote2/remotemessage_pb2.py
androidtvremote2/remotemessage_pb2.pyi
androidtvremote2-0.2.3.dist-info/licenses/LICENSE
androidtvremote2-0.2.3.dist-info/METADATA
androidtvremote2-0.2.3.dist-info/WHEEL
androidtvremote2-0.2.3.dist-info/top_level.txt
androidtvremote2-0.2.3.dist-info/RECORD
