Metadata-Version: 2.4
Name: androidtvremote2
Version: 0.2.3
Summary: A Python library for interacting with Android TV using the Android TV Remote protocol v2
Author-email: tronikos <tronikos@gmail.com>
License: Apache-2.0
Project-URL: Homepage, https://github.com/tronikos/androidtvremote2
Project-URL: Bug Tracker, https://github.com/tronikos/androidtvremote2/issues
Requires-Python: >=3.10
License-File: LICENSE
Requires-Dist: aiofiles>=0.8
Requires-Dist: cryptography>=3
Requires-Dist: protobuf>=4.21
Dynamic: license-file
